fastsae/__init__.py
fastsae-0.0.1.dist-info/licenses/LICENSE
fastsae-0.0.1.dist-info/METADATA
fastsae-0.0.1.dist-info/WHEEL
fastsae-0.0.1.dist-info/top_level.txt
fastsae-0.0.1.dist-info/RECORD
