Metadata-Version: 2.4
Name: fastsae
Version: 0.0.1
Summary: Fast Sparse Autoencoder library
Author-email: Schneider Lab <stes@hey.com>
Classifier: Development Status :: 3 - Alpha
Classifier: Intended Audience :: Developers
Classifier: Intended Audience :: Science/Research
Classifier: Programming Language :: Python :: 3
Classifier: Programming Language :: Python :: 3.10
Classifier: Programming Language :: Python :: 3.11
Classifier: Programming Language :: Python :: 3.12
Classifier: Topic :: Scientific/Engineering :: Artificial Intelligence
Requires-Python: >=3.10
License-File: LICENSE
Provides-Extra: dev
Dynamic: license-file
